odoo10_addon_barcodes_generator_picking-10.0.1.0.0-py2.7-nspkg.pth
odoo/addons/barcodes_generator_picking/README.rst
odoo/addons/barcodes_generator_picking/__init__.py
odoo/addons/barcodes_generator_picking/__manifest__.py
odoo/addons/barcodes_generator_picking/demo/barcode_rule.xml
odoo/addons/barcodes_generator_picking/demo/function.xml
odoo/addons/barcodes_generator_picking/demo/ir_sequence.xml
odoo/addons/barcodes_generator_picking/demo/stock_picking.xml
odoo/addons/barcodes_generator_picking/i18n/fr.po
odoo/addons/barcodes_generator_picking/models/__init__.py
odoo/addons/barcodes_generator_picking/models/barcode_rule.py
odoo/addons/barcodes_generator_picking/models/stock_picking.py
odoo/addons/barcodes_generator_picking/static/description/icon.png
odoo/addons/barcodes_generator_picking/static/description/stock_picking_sequence_generation.png
odoo/addons/barcodes_generator_picking/tests/__init__.py
odoo/addons/barcodes_generator_picking/tests/test_barcode_generator.py
odoo/addons/barcodes_generator_picking/views/stock_picking.xml
odoo10_addon_barcodes_generator_picking-10.0.1.0.0.dist-info/DESCRIPTION.rst
odoo10_addon_barcodes_generator_picking-10.0.1.0.0.dist-info/METADATA
odoo10_addon_barcodes_generator_picking-10.0.1.0.0.dist-info/RECORD
odoo10_addon_barcodes_generator_picking-10.0.1.0.0.dist-info/WHEEL
odoo10_addon_barcodes_generator_picking-10.0.1.0.0.dist-info/metadata.json
odoo10_addon_barcodes_generator_picking-10.0.1.0.0.dist-info/namespace_packages.txt
odoo10_addon_barcodes_generator_picking-10.0.1.0.0.dist-info/top_level.txt
